{
    "os": "Linux-5.10.102.1-microsoft-standard-WSL2-x86_64-with-glibc2.31",
    "python": "3.10.6",
    "heartbeatAt": "2022-11-18T17:48:40.831689",
    "startedAt": "2022-11-18T17:48:39.972950",
    "docker": null,
    "cuda": null,
    "args": [
        "-s",
        "-m",
        "etl"
    ],
    "state": "running",
    "program": "/home/john/anaconda3/envs/recsys/bin/pytest",
    "git": {
        "remote": null,
        "commit": "a497754b55221d94b6578f4cbde4a58bdf4f66af"
    },
    "email": "john.james.ai.studio@gmail.com",
    "root": "/home/john/smartify/recsys",
    "host": "Leviathan",
    "username": "john",
    "executable": "/home/john/anaconda3/envs/recsys/bin/python3.10",
    "cpu_count": 12,
    "cpu_count_logical": 24,
    "cpu_freq": {
        "current": 2659.998999999998,
        "min": 0.0,
        "max": 0.0
    },
    "cpu_freq_per_core": [
        {
            "current": 2659.999,
            "min": 0.0,
            "max": 0.0
        },
        {
            "current": 2659.999,
            "min": 0.0,
            "max": 0.0
        },
        {
            "current": 2659.999,
            "min": 0.0,
            "max": 0.0
        },
        {
            "current": 2659.999,
            "min": 0.0,
            "max": 0.0
        },
        {
            "current": 2659.999,
            "min": 0.0,
            "max": 0.0
        },
        {
            "current": 2659.999,
            "min": 0.0,
            "max": 0.0
        },
        {
            "current": 2659.999,
            "min": 0.0,
            "max": 0.0
        },
        {
            "current": 2659.999,
            "min": 0.0,
            "max": 0.0
        },
        {
            "current": 2659.999,
            "min": 0.0,
            "max": 0.0
        },
        {
            "current": 2659.999,
            "min": 0.0,
            "max": 0.0
        },
        {
            "current": 2659.999,
            "min": 0.0,
            "max": 0.0
        },
        {
            "current": 2659.999,
            "min": 0.0,
            "max": 0.0
        },
        {
            "current": 2659.999,
            "min": 0.0,
            "max": 0.0
        },
        {
            "current": 2659.999,
            "min": 0.0,
            "max": 0.0
        },
        {
            "current": 2659.999,
            "min": 0.0,
            "max": 0.0
        },
        {
            "current": 2659.999,
            "min": 0.0,
            "max": 0.0
        },
        {
            "current": 2659.999,
            "min": 0.0,
            "max": 0.0
        },
        {
            "current": 2659.999,
            "min": 0.0,
            "max": 0.0
        },
        {
            "current": 2659.999,
            "min": 0.0,
            "max": 0.0
        },
        {
            "current": 2659.999,
            "min": 0.0,
            "max": 0.0
        },
        {
            "current": 2659.999,
            "min": 0.0,
            "max": 0.0
        },
        {
            "current": 2659.999,
            "min": 0.0,
            "max": 0.0
        },
        {
            "current": 2659.999,
            "min": 0.0,
            "max": 0.0
        },
        {
            "current": 2659.999,
            "min": 0.0,
            "max": 0.0
        }
    ],
    "disk": {
        "total": 491.152587890625,
        "used": 56.73862075805664
    },
    "gpu": "Quadro P400",
    "gpu_count": 1,
    "gpu_devices": [
        {
            "name": "Quadro P400",
            "memory_total": 2147483648
        }
    ],
    "memory": {
        "total": 100.5960578918457
    }
}
